GeneratePasswords/__init__.py
raniapasswordmaker-0.1.0.dist-info/METADATA
raniapasswordmaker-0.1.0.dist-info/WHEEL
raniapasswordmaker-0.1.0.dist-info/top_level.txt
raniapasswordmaker-0.1.0.dist-info/RECORD
