Metadata-Version: 2.4
Name: RaniaPasswordMaker
Version: 0.1.0
Summary: A program that generates passwords with the required number and conditions.
Author: Rania_Elkholy
License: MIT
Project-URL: Homepage, https://pypi.org/project/GeneratePasswords/
Keywords: password,generator,security
Classifier: Programming Language :: Python :: 3
Classifier: License :: OSI Approved :: MIT License
Classifier: Operating System :: OS Independent
